{"version":1,"resource":"file:///home/brayan/work/web/app/views/async/remunerations/_worked_days_table_row.html.haml","entries":[{"id":"1WrA.haml","timestamp":1701191994292},{"id":"tJTv.haml","timestamp":1701192016264},{"id":"qT1B.haml","source":"undoRedo.source","timestamp":1701192022692},{"id":"YapB.haml","timestamp":1701192057104},{"id":"9w36.haml","timestamp":1701192078972},{"id":"pcnR.haml","timestamp":1701192113768},{"id":"eMmI.haml","timestamp":1701192177240},{"id":"wVkh.haml","timestamp":1701192226508},{"id":"uCET.haml","timestamp":1701192460144},{"id":"2Ced.haml","timestamp":1701192480624},{"id":"Am2d.haml","timestamp":1701192497624},{"id":"d1se.haml","timestamp":1701192536960},{"id":"V5Il.haml","timestamp":1701192580884},{"id":"qePb.haml","timestamp":1701192696528},{"id":"YmIC.haml","timestamp":1701192829660},{"id":"3gXV.haml","timestamp":1701192847248},{"id":"0Ml2.haml","source":"undoRedo.source","timestamp":1701192861559},{"id":"yTnM.haml","timestamp":1701192917027},{"id":"JCv9.haml","timestamp":1701277941760},{"id":"pqRH.haml","timestamp":1701280527470},{"id":"HZCm.haml","timestamp":1701714610415},{"id":"k9Hs.haml","timestamp":1701717837728},{"id":"jHgJ.haml","timestamp":1701717908716},{"id":"wf6O.haml","timestamp":1701717932780},{"id":"iRi4.haml","timestamp":1701886959279},{"id":"7mHm.haml","timestamp":1701886978575},{"id":"kX61.haml","timestamp":1701886996091},{"id":"BCiY.haml","timestamp":1701959906474},{"id":"1UoO.haml","timestamp":1701974174113},{"id":"KFLm.haml","timestamp":1701980381060},{"id":"rSt2.haml","timestamp":1703096629012},{"id":"nSdp.haml","timestamp":1703096671512},{"id":"4yav.haml","timestamp":1703096703356},{"id":"DUVo.haml","timestamp":1703096723808},{"id":"hr29.haml","timestamp":1703096754900},{"id":"cq6s.haml","timestamp":1703096776280},{"id":"0WjA.haml","timestamp":1703096829060},{"id":"wsc2.haml","timestamp":1703097039984},{"id":"5oze.haml","source":"undoRedo.source","timestamp":1703097064260},{"id":"NPg9.haml","timestamp":1703097109480},{"id":"bQx8.haml","timestamp":1703102733279},{"id":"JzY9.haml","timestamp":1703102841449},{"id":"bA9t.haml","timestamp":1703102890892},{"id":"X801.haml","timestamp":1703102905880},{"id":"m05i.haml","timestamp":1703102921200},{"id":"2VTO.haml","timestamp":1703103077715},{"id":"jv7g.haml","timestamp":1703103098739},{"id":"qiQ0.haml","timestamp":1703103241366},{"id":"V1bl.haml","timestamp":1703103283013},{"id":"xGXu.haml","timestamp":1703103411553}]}