{"version":1,"resource":"file:///home/brayan/work/web/app/views/async/remunerations/_licenses_table_row.html.haml","entries":[{"id":"4PD8.haml","timestamp":1702408168224},{"id":"bVOF.haml","source":"undoRedo.source","timestamp":1702408172672},{"id":"KI3S.haml","timestamp":1702408183700},{"id":"gHVb.haml","timestamp":1702408203588},{"id":"J9gV.haml","source":"undoRedo.source","timestamp":1702408208428},{"id":"IbFM.haml","timestamp":1702408264441},{"id":"R6vL.haml","timestamp":1702408300001},{"id":"DrOE.haml","timestamp":1702408326029},{"id":"QcgE.haml","timestamp":1702408475817},{"id":"3A5O.haml","timestamp":1702408503145},{"id":"WWsw.haml","timestamp":1702408517109},{"id":"XiHE.haml","timestamp":1702408617105},{"id":"WQI1.haml","timestamp":1702408696233},{"id":"0rrF.haml","timestamp":1702408710445},{"id":"WWDd.haml","timestamp":1702409934878},{"id":"ncKX.haml","timestamp":1702410032691},{"id":"PGwU.haml","timestamp":1702492741346},{"id":"Ip0h.haml","timestamp":1702492976790},{"id":"1s9l.haml","timestamp":1702493010202},{"id":"uFM3.haml","timestamp":1702493051002},{"id":"jAEY.haml","timestamp":1702493749394},{"id":"7ItU.haml","timestamp":1702493771530},{"id":"GPND.haml","source":"undoRedo.source","timestamp":1702494024783},{"id":"0lQp.haml","timestamp":1702494487535},{"id":"KdhB.haml","timestamp":1702494530163},{"id":"os0d.haml","source":"undoRedo.source","timestamp":1702494639387},{"id":"AwYo.haml","timestamp":1702494682579},{"id":"HUQP.haml","timestamp":1702494710831},{"id":"T4M5.haml","timestamp":1702494754719},{"id":"bAqP.haml","source":"undoRedo.source","timestamp":1702494841243},{"id":"6YXF.haml","timestamp":1702494914899},{"id":"wRZt.haml","timestamp":1702495008828},{"id":"BtOT.haml","timestamp":1702495118448},{"id":"H3tO.haml","timestamp":1702495143924},{"id":"DXku.haml","timestamp":1702495163852},{"id":"sx8R.haml","timestamp":1702495213512},{"id":"nsOW.haml","timestamp":1702495225332},{"id":"U2FE.haml","timestamp":1702495318684},{"id":"opyv.haml","timestamp":1702495388076},{"id":"dwWA.haml","timestamp":1702495400656},{"id":"6TJG.haml","timestamp":1702495411908},{"id":"dmiJ.haml","source":"undoRedo.source","timestamp":1702495452312},{"id":"2iZe.haml","timestamp":1702495473888},{"id":"gNFZ.haml","timestamp":1702567385553},{"id":"y3Bq.haml","timestamp":1702568006486},{"id":"eYwk.haml","timestamp":1702568049742},{"id":"4bLL.haml","timestamp":1702568256762},{"id":"tfS3.haml","timestamp":1702568343110},{"id":"dDPI.haml","timestamp":1702568843021},{"id":"7Dnj.haml","timestamp":1702587300193}]}